pycutwm/__init__.py
pycutwm/build.py
pycutwm/core.py
pycutwm/plot_tools.py
pycutwm/power_xy.py
pycutwm/ref_ind_crystals.py
pycutwm/utils.py
pycutwm-0.1.0.dist-info/METADATA
pycutwm-0.1.0.dist-info/WHEEL
pycutwm-0.1.0.dist-info/top_level.txt
pycutwm-0.1.0.dist-info/RECORD
