Metadata-Version: 2.4
Name: pycutwm
Version: 0.1.0
Summary: Modelling tools for package cuTWM(3+1)D
Author: Alfredo Daniel Sanchez
Requires-Python: >=3.8
Requires-Dist: numpy
Requires-Dist: matplotlib
Requires-Dist: imageio
Dynamic: author
Dynamic: requires-dist
Dynamic: requires-python
Dynamic: summary
